financier/__init__.py
financier/multiplication.py
financier-0.1.1.dist-info/LICENSE
financier-0.1.1.dist-info/METADATA
financier-0.1.1.dist-info/WHEEL
financier-0.1.1.dist-info/top_level.txt
financier-0.1.1.dist-info/RECORD
