Metadata-Version: 2.1
Name: financier
Version: 0.1.1
Summary: Demo library
Home-page: https://financier.readthedocs.io/
Author: Jake Vestal, Sophie Rubin
Author-email: jmvestal@gmail.com, example@email.com
License: MIT
Platform: UNKNOWN
Classifier: Intended Audience :: Developers
Classifier: License :: OSI Approved :: MIT License
Classifier: Programming Language :: Python
Classifier: Programming Language :: Python :: 3
Classifier: Programming Language :: Python :: 3.9
Classifier: Operating System :: OS Independent
Requires-Dist: numpy
